coppyr/__init__.py
coppyr/config.py
coppyr/context.py
coppyr/daemon.py
coppyr/error.py
coppyr/logger.py
coppyr/package.py
coppyr/testing.py
coppyr/web.py
coppyr/collections/__init__.py
coppyr/collections/cycle.py
coppyr/collections/dotdict.py
coppyr/extensions/__init__.py
coppyr/extensions/load.py
coppyr/process/__init__.py
coppyr/process/concurrent.py
coppyr/process/parallel.py
coppyr/process/subp.py
coppyr/types/__init__.py
coppyr/types/differ.py
coppyr/types/lazyproperty.py
coppyr/types/singleton.py
coppyr/types/slot.py
coppyr-0.9.4.dist-info/LICENSE
coppyr-0.9.4.dist-info/METADATA
coppyr-0.9.4.dist-info/WHEEL
coppyr-0.9.4.dist-info/top_level.txt
coppyr-0.9.4.dist-info/RECORD
