Metadata-Version: 2.1
Name: coppyr
Version: 0.9.4
Summary: A collection of boilerplate for Python applications.
Home-page: https://github.com/gshulegaard/coppyr
Author: Grant Hulegaard
Author-email: loki.labrys@gmail.com
License: MIT
Classifier: Development Status :: 4 - Beta
Classifier: Intended Audience :: Developers
Classifier: License :: OSI Approved :: MIT License
Classifier: Programming Language :: Python
Classifier: Programming Language :: Python :: 3
Classifier: Programming Language :: Python :: Implementation :: CPython
License-File: LICENSE
Provides-Extra: all
Requires-Dist: PyYAML ; extra == 'all'
Requires-Dist: toml ; extra == 'all'
Requires-Dist: python-daemon ==2.3.2 ; extra == 'all'
Requires-Dist: pip >=10 ; extra == 'all'
Provides-Extra: config
Requires-Dist: PyYAML ; extra == 'config'
Requires-Dist: toml ; extra == 'config'
Provides-Extra: daemon
Requires-Dist: python-daemon ==2.3.2 ; extra == 'daemon'
Provides-Extra: dev
Requires-Dist: build ; extra == 'dev'
Requires-Dist: pytest ; extra == 'dev'
Requires-Dist: pytest-xdist ; extra == 'dev'
Requires-Dist: semver ; extra == 'dev'
Requires-Dist: tox ; extra == 'dev'
Requires-Dist: twine ; extra == 'dev'
Provides-Extra: pkg
Requires-Dist: pip >=10 ; extra == 'pkg'
